{"patient":{"0":"RB43","1":"RB43","2":"RB43","3":"RB43","4":"RB43","5":"RB43","6":"RB43","7":"RB43","8":"RB43","9":"RB43","10":"RB43","11":"RB43","12":"RB43","13":"RB43"},"topic":{"0":"T1","1":"T2","2":"T3","3":"T4","4":"T5","5":"T6","6":"T7","7":"T8","8":"T9","9":"T10","10":"T11","11":"T12","12":"T13","13":"T14"},"label":{"0":2,"1":2,"2":2,"3":2,"4":2,"5":2,"6":2,"7":2,"8":2,"9":2,"10":2,"11":2,"12":2,"13":2},"text":{"0":"[derau].","1":"[derau].. Sudah sudah.","2":"[derau].[derau].","3":"..","4":"[derau].","5":"[derau].. Kawan kawan, kawan, talawi. Kawan talawi. Sudah [derau].","6":"[derau][derau].[ee] [ee].","7":". Sudah sudah","8":"morning[derau] [derau].","9":"[derau].[derau].","10":"[derau]morning[derau].","11":"[derau] morning,morning,permanen yuk, lanjut yuk.[derau] sudah","12":"..","13":"[derau]morning.matahari[derau]."}}